<?xml version = '1.0' encoding = 'UTF-8'?>
<Relation class="oracle.dbtools.crest.model.design.logical.Relation" name="d_asig" directorySegmentName="seg_0" id="A830FF40-630F-A826-62EC-8315BF704463">
<createdBy>Alumno02</createdBy>
<createdTime>2023-08-28 13:21:17 UTC</createdTime>
<ownerDesignName>Modelo_logico</ownerDesignName>
<engineerTo>
<item key="BAB9447F-2E08-F283-3145-72327BED06B4" value="true"/>
</engineerTo>
<identifying>false</identifying>
<optionalSource>true</optionalSource>
<optionalTarget>true</optionalTarget>
<sourceCardinality>*</sourceCardinality>
<sourceEntity>6F57C091-9DA3-CC8E-3C34-6591BEB7A09C</sourceEntity>
<targetCardinalityString>*</targetCardinalityString>
<targetEntity>346329E8-23E5-A2EE-4566-BE065DAF950D</targetEntity>
<transferable>true</transferable>
<deleteRule>NO ACTION</deleteRule>
</Relation>
